infiniloom/__init__.py
infiniloom/_async.py
infiniloom/_infiniloom.pypy310-pp73-aarch64-linux-gnu.so
infiniloom/models.py
infiniloom/py.typed
infiniloom-0.6.3.dist-info/METADATA
infiniloom-0.6.3.dist-info/WHEEL
infiniloom-0.6.3.dist-info/RECORD
