Metadata-Version: 2.4
Name: infiniloom
Version: 0.6.3
Classifier: Development Status :: 3 - Alpha
Classifier: Intended Audience :: Developers
Classifier: License :: OSI Approved :: MIT License
Classifier: Programming Language :: Python :: 3
Classifier: Programming Language :: Python :: 3.8
Classifier: Programming Language :: Python :: 3.9
Classifier: Programming Language :: Python :: 3.10
Classifier: Programming Language :: Python :: 3.11
Classifier: Programming Language :: Python :: 3.12
Classifier: Programming Language :: Rust
Classifier: Topic :: Software Development :: Libraries
Requires-Dist: pydantic>=2.0.0
Requires-Dist: pytest>=7.0 ; extra == 'dev'
Requires-Dist: pytest-asyncio>=0.21.0 ; extra == 'dev'
Requires-Dist: pyrefly>=0.18.0 ; extra == 'dev'
Requires-Dist: mypy>=1.0.0 ; extra == 'dev'
Provides-Extra: dev
Summary: Python bindings for Infiniloom - AST-aware code context engine for RAG and vector databases. Tree-sitter parsing, PageRank ranking, BLAKE3 content-addressable chunks, 27+ tokenizers.
Keywords: llm,rag,retrieval-augmented-generation,vector-database,pinecone,weaviate,qdrant,chromadb,embeddings,code-context,code-analysis,ast,tree-sitter,pagerank,content-addressable,blake3,claude,gpt4o,gpt5,gemini,llama,tiktoken,code-chunking,semantic-chunking
Author-email: Topos Labs <hello@toposlabs.ai>
License: MIT
Requires-Python: >=3.8
Project-URL: Documentation, https://toposlabs.ai/infiniloom/
Project-URL: Homepage, https://toposlabs.ai/infiniloom/
Project-URL: Repository, https://github.com/Topos-Labs/infiniloom
